<?xml version='1.0' encoding='UTF-8'?>
<AnalysisInput>
  <Settings>
    <Setting>
      <Key>sonar.cs.ignoreHeaderComments</Key>
      <Value>true</Value>
    </Setting>
  </Settings>
  <Rules>
    <Rule>
      <Key>S101</Key>
      <Parameters/>
    </Rule>
    <Rule>
      <Key>S103</Key>
      <Parameters>
        <Parameter>
          <Key>maximumLineLength</Key>
          <Value>140</Value>
        </Parameter>
      </Parameters>
    </Rule>
    <Rule>
      <Key>S104</Key>
      <Parameters>
        <Parameter>
          <Key>maximumFileLocThreshold</Key>
          <Value>500</Value>
        </Parameter>
      </Parameters>
    </Rule>
    <Rule>
      <Key>S105</Key>
      <Parameters/>
    </Rule>
    <Rule>
      <Key>S107</Key>
      <Parameters>
        <Parameter>
          <Key>max</Key>
          <Value>6</Value>
        </Parameter>
      </Parameters>
    </Rule>
    <Rule>
      <Key>S110</Key>
      <Parameters>
        <Parameter>
          <Key>max</Key>
          <Value>4</Value>
        </Parameter>
      </Parameters>
    </Rule>
    <Rule>
      <Key>S1116</Key>
      <Parameters/>
    </Rule>
    <Rule>
      <Key>S1118</Key>
      <Parameters/>
    </Rule>
    <Rule>
      <Key>S112</Key>
      <Parameters/>
    </Rule>
    <Rule>
      <Key>S1121</Key>
      <Parameters/>
    </Rule>
    <Rule>
      <Key>S1163</Key>
      <Parameters/>
    </Rule>
    <Rule>
      <Key>S1172</Key>
      <Parameters/>
    </Rule>
    <Rule>
      <Key>S1206</Key>
      <Parameters/>
    </Rule>
    <Rule>
      <Key>S1210</Key>
      <Parameters/>
    </Rule>
    <Rule>
      <Key>S1215</Key>
      <Parameters/>
    </Rule>
    <Rule>
      <Key>S122</Key>
      <Parameters/>
    </Rule>
    <Rule>
      <Key>S1226</Key>
      <Parameters/>
    </Rule>
    <Rule>
      <Key>S1244</Key>
      <Parameters/>
    </Rule>
    <Rule>
      <Key>S125</Key>
      <Parameters/>
    </Rule>
    <Rule>
      <Key>S131</Key>
      <Parameters/>
    </Rule>
    <Rule>
      <Key>S1481</Key>
      <Parameters/>
    </Rule>
    <Rule>
      <Key>S1541</Key>
      <Parameters>
        <Parameter>
          <Key>maximumFunctionComplexityThreshold</Key>
          <Value>25</Value>
        </Parameter>
      </Parameters>
    </Rule>
    <Rule>
      <Key>S1656</Key>
      <Parameters/>
    </Rule>
    <Rule>
      <Key>S2156</Key>
      <Parameters/>
    </Rule>
    <Rule>
      <Key>S2184</Key>
      <Parameters/>
    </Rule>
    <Rule>
      <Key>S2190</Key>
      <Parameters/>
    </Rule>
    <Rule>
      <Key>S2197</Key>
      <Parameters/>
    </Rule>
    <Rule>
      <Key>S2223</Key>
      <Parameters/>
    </Rule>
    <Rule>
      <Key>S2225</Key>
      <Parameters/>
    </Rule>
    <Rule>
      <Key>S2306</Key>
      <Parameters/>
    </Rule>
    <Rule>
      <Key>S2342</Key>
      <Parameters>
        <Parameter>
          <Key>format</Key>
          <Value>^([A-Z]{1,3}[a-z0-9]+)*([A-Z]{2})?$</Value>
        </Parameter>
        <Parameter>
          <Key>flagsAttributeFormat</Key>
          <Value>^([A-Z]{1,3}[a-z0-9]+)*([A-Z]{2})?s$</Value>
        </Parameter>
      </Parameters>
    </Rule>
    <Rule>
      <Key>S2346</Key>
      <Parameters/>
    </Rule>
    <Rule>
      <Key>S2357</Key>
      <Parameters/>
    </Rule>
    <Rule>
      <Key>S2372</Key>
      <Parameters/>
    </Rule>
    <Rule>
      <Key>S2376</Key>
      <Parameters/>
    </Rule>
    <Rule>
      <Key>S2551</Key>
      <Parameters/>
    </Rule>
    <Rule>
      <Key>S2688</Key>
      <Parameters/>
    </Rule>
    <Rule>
      <Key>S2696</Key>
      <Parameters/>
    </Rule>
    <Rule>
      <Key>S2743</Key>
      <Parameters/>
    </Rule>
    <Rule>
      <Key>S2757</Key>
      <Parameters/>
    </Rule>
    <Rule>
      <Key>S2930</Key>
      <Parameters/>
    </Rule>
    <Rule>
      <Key>S2931</Key>
      <Parameters/>
    </Rule>
    <Rule>
      <Key>S2952</Key>
      <Parameters/>
    </Rule>
    <Rule>
      <Key>S2971</Key>
      <Parameters/>
    </Rule>
    <Rule>
      <Key>S3005</Key>
      <Parameters/>
    </Rule>
    <Rule>
      <Key>S3052</Key>
      <Parameters/>
    </Rule>
    <Rule>
      <Key>S3234</Key>
      <Parameters/>
    </Rule>
    <Rule>
      <Key>S3237</Key>
      <Parameters/>
    </Rule>
    <Rule>
      <Key>S3242</Key>
      <Parameters/>
    </Rule>
    <Rule>
      <Key>S3247</Key>
      <Parameters/>
    </Rule>
    <Rule>
      <Key>S3256</Key>
      <Parameters/>
    </Rule>
    <Rule>
      <Key>S3261</Key>
      <Parameters/>
    </Rule>
    <Rule>
      <Key>S3376</Key>
      <Parameters/>
    </Rule>
    <Rule>
      <Key>S3442</Key>
      <Parameters/>
    </Rule>
    <Rule>
      <Key>S3443</Key>
      <Parameters/>
    </Rule>
    <Rule>
      <Key>S3445</Key>
      <Parameters/>
    </Rule>
    <Rule>
      <Key>S3457</Key>
      <Parameters/>
    </Rule>
    <Rule>
      <Key>S3459</Key>
      <Parameters/>
    </Rule>
    <Rule>
      <Key>S3776</Key>
      <Parameters>
        <Parameter>
          <Key>threshold</Key>
          <Value>15</Value>
        </Parameter>
        <Parameter>
          <Key>propertyThreshold</Key>
          <Value>3</Value>
        </Parameter>
      </Parameters>
    </Rule>
    <Rule>
      <Key>S3869</Key>
      <Parameters/>
    </Rule>
    <Rule>
      <Key>S3871</Key>
      <Parameters/>
    </Rule>
    <Rule>
      <Key>S3872</Key>
      <Parameters/>
    </Rule>
    <Rule>
      <Key>S3874</Key>
      <Parameters/>
    </Rule>
    <Rule>
      <Key>S3875</Key>
      <Parameters/>
    </Rule>
    <Rule>
      <Key>S3876</Key>
      <Parameters/>
    </Rule>
    <Rule>
      <Key>S3877</Key>
      <Parameters/>
    </Rule>
    <Rule>
      <Key>S3880</Key>
      <Parameters/>
    </Rule>
    <Rule>
      <Key>S3881</Key>
      <Parameters/>
    </Rule>
    <Rule>
      <Key>S3884</Key>
      <Parameters/>
    </Rule>
    <Rule>
      <Key>S3885</Key>
      <Parameters/>
    </Rule>
    <Rule>
      <Key>S3887</Key>
      <Parameters/>
    </Rule>
    <Rule>
      <Key>S3889</Key>
      <Parameters/>
    </Rule>
    <Rule>
      <Key>S3903</Key>
      <Parameters/>
    </Rule>
    <Rule>
      <Key>S3906</Key>
      <Parameters/>
    </Rule>
    <Rule>
      <Key>S3908</Key>
      <Parameters/>
    </Rule>
    <Rule>
      <Key>S3909</Key>
      <Parameters/>
    </Rule>
    <Rule>
      <Key>S3925</Key>
      <Parameters/>
    </Rule>
    <Rule>
      <Key>S3926</Key>
      <Parameters/>
    </Rule>
    <Rule>
      <Key>S3927</Key>
      <Parameters/>
    </Rule>
    <Rule>
      <Key>S3928</Key>
      <Parameters/>
    </Rule>
    <Rule>
      <Key>S3956</Key>
      <Parameters/>
    </Rule>
    <Rule>
      <Key>S3962</Key>
      <Parameters/>
    </Rule>
    <Rule>
      <Key>S3963</Key>
      <Parameters/>
    </Rule>
    <Rule>
      <Key>S3996</Key>
      <Parameters/>
    </Rule>
    <Rule>
      <Key>S3997</Key>
      <Parameters/>
    </Rule>
    <Rule>
      <Key>S3998</Key>
      <Parameters/>
    </Rule>
    <Rule>
      <Key>S4002</Key>
      <Parameters/>
    </Rule>
    <Rule>
      <Key>S4016</Key>
      <Parameters/>
    </Rule>
    <Rule>
      <Key>S4017</Key>
      <Parameters/>
    </Rule>
    <Rule>
      <Key>S4018</Key>
      <Parameters/>
    </Rule>
    <Rule>
      <Key>S4019</Key>
      <Parameters/>
    </Rule>
    <Rule>
      <Key>S4022</Key>
      <Parameters/>
    </Rule>
    <Rule>
      <Key>S4023</Key>
      <Parameters/>
    </Rule>
    <Rule>
      <Key>S4027</Key>
      <Parameters/>
    </Rule>
    <Rule>
      <Key>S4039</Key>
      <Parameters/>
    </Rule>
    <Rule>
      <Key>S4040</Key>
      <Parameters/>
    </Rule>
    <Rule>
      <Key>S4041</Key>
      <Parameters/>
    </Rule>
    <Rule>
      <Key>S4047</Key>
      <Parameters/>
    </Rule>
    <Rule>
      <Key>S4050</Key>
      <Parameters/>
    </Rule>
    <Rule>
      <Key>S4056</Key>
      <Parameters/>
    </Rule>
    <Rule>
      <Key>S4057</Key>
      <Parameters/>
    </Rule>
    <Rule>
      <Key>S4058</Key>
      <Parameters/>
    </Rule>
    <Rule>
      <Key>S4059</Key>
      <Parameters/>
    </Rule>
    <Rule>
      <Key>S4060</Key>
      <Parameters/>
    </Rule>
    <Rule>
      <Key>S4069</Key>
      <Parameters/>
    </Rule>
    <Rule>
      <Key>S4214</Key>
      <Parameters/>
    </Rule>  </Rules>
</AnalysisInput>